clip/__init__.py
clip/ffmpeg_info.py
clip/frame.py
clip/guess.py
moviepy_utils-1.0.3.dist-info/METADATA
moviepy_utils-1.0.3.dist-info/WHEEL
moviepy_utils-1.0.3.dist-info/top_level.txt
moviepy_utils-1.0.3.dist-info/RECORD
